hmcscanner/__init__.py
hmcscanner/dataCollector.py
hmcscanner/data_parser.py
hmcscanner/excelWriter.py
hmcscanner/hmcClient.py
hmcscanner/scanner.py
hmcscanner/start.py
hmcscanner/tqdm_manager.py
hmcscanner-0.8.dist-info/LICENSE
hmcscanner-0.8.dist-info/METADATA
hmcscanner-0.8.dist-info/WHEEL
hmcscanner-0.8.dist-info/entry_points.txt
hmcscanner-0.8.dist-info/top_level.txt
hmcscanner-0.8.dist-info/RECORD
